deki/__init__.py
deki/rosenbrock.py
deki/sphere.py
deki/visualizer.py
deki-0.0.1.dev1.dist-info/LICENSE
deki-0.0.1.dev1.dist-info/METADATA
deki-0.0.1.dev1.dist-info/WHEEL
deki-0.0.1.dev1.dist-info/top_level.txt
deki-0.0.1.dev1.dist-info/RECORD
